{
  "packageId": "app.vercel.vivienda_ya.twa",
  "host": "vivienda-ya.vercel.app",
  "name": "vivienda ya",
  "launcherName": "ViviendaYa",
  "display": "fullscreen",
  "themeColor": "#000000",
  "themeColorDark": "#000000",
  "navigationColor": "#000000",
  "navigationColorDark": "#000000",
  "navigationDividerColor": "#000000",
  "navigationDividerColorDark": "#000000",
  "backgroundColor": "#22C55E",
  "enableNotifications": true,
  "startUrl": "/feed?utm_source=pwa",
  "iconUrl": "https://vivienda-ya.vercel.app/icon-512.png",
  "splashScreenFadeOutDuration": 300,
  "signingKey": {
    "path": "C:\\proyectos\\vivienda-ya\\viviendaya-new.keystore",
    "alias": "viviendaya"
  },
  "appVersionName": "3",
  "appVersionCode": 3,
  "shortcuts": [],
  "generatorApp": "bubblewrap-cli",
  "webManifestUrl": "https://vivienda-ya.vercel.app/manifest.json",
  "fallbackType": "customtabs",
  "features": {
    "playBilling": {
      "enabled": true
    },
    "locationDelegation": {
      "enabled": true
    }
  },
  "alphaDependencies": {
    "enabled": false
  },
  "enableSiteSettingsShortcut": true,
  "isChromeOSOnly": false,
  "isMetaQuest": false,
  "fullScopeUrl": "https://vivienda-ya.vercel.app/",
  "minSdkVersion": 21,
  "orientation": "portrait",
  "fingerprints": [
    "56:07:E1:5C:B4:F8:BD:49:1E:9E:08:C1:E1:18:CB:47:D1:9A:E4:AB:F7:1E:4F:3F:CA:28:AC:88:C0:3A:4B:6B"
  ],
  "additionalTrustedOrigins": [],
  "retainedBundles": [],
  "protocolHandlers": [],
  "fileHandlers": [],
  "launchHandlerClientMode": "",
  "displayOverride": [],
  "appVersion": "3"
}